{
  "id": "live-corales-puntacana-championship",
  "name": "Corales Puntacana Championship",
  "tour": "PGA Tour",
  "course": "—",
  "dates": null,
  "par": 71,
  "yards": 0,
  "startDate": "2026-07-16T04:00Z",
  "snapshotAt": "2026-07-21T08:42:25+00:00",
  "headlines": {
    "torsdag": "Mazzoli soloar på -20 – Sargent och Clements förlorar slag på Puntacana",
    "fredag": "Mazzoli solklar på -20 när Gordon och Clements jagade på -19",
    "lordag": "Mazzoli dominerar Puntacana – Italienaren straffar på -20 före Sargent och Clements",
    "sondag": "Mazzoli solär bort från Sargent och Clements på Puntacana – vinner med tjugo under par"
  },
  "finalLeaderboard": [
    {
      "position": "1",
      "name": "Stefano Mazzoli",
      "country": "Italy",
      "totalDisplay": "-20",
      "totalValue": -20.0,
      "rounds": [
        "-5",
        "-3",
        "-6",
        "-6"
      ]
    },
    {
      "position": "T2",
      "name": "Gordon Sargent",
      "country": "USA",
      "totalDisplay": "-19",
      "totalValue": -19.0,
      "rounds": [
        "-6",
        "-5",
        "-3",
        "-5"
      ]
    },
    {
      "position": "T2",
      "name": "Todd Clements",
      "country": "England",
      "totalDisplay": "-19",
      "totalValue": -19.0,
      "rounds": [
        "-7",
        "-6",
        "-5",
        "-1"
      ]
    },
    {
      "position": "T4",
      "name": "Will Gordon",
      "country": "USA",
      "totalDisplay": "-18",
      "totalValue": -18.0,
      "rounds": [
        "-3",
        "-2",
        "-7",
        "-6"
      ]
    },
    {
      "position": "T4",
      "name": "Ben James",
      "country": "USA",
      "totalDisplay": "-18",
      "totalValue": -18.0,
      "rounds": [
        "-5",
        "-6",
        "-5",
        "-2"
      ]
    },
    {
      "position": "T6",
      "name": "Marcel Schneider",
      "country": "Germany",
      "totalDisplay": "-17",
      "totalValue": -17.0,
      "rounds": [
        "-2",
        "-6",
        "-5",
        "-4"
      ]
    },
    {
      "position": "T6",
      "name": "Jacob Skov Olesen",
      "country": "Denmark",
      "totalDisplay": "-17",
      "totalValue": -17.0,
      "rounds": [
        "-5",
        "-3",
        "-5",
        "-4"
      ]
    },
    {
      "position": "T6",
      "name": "Joe Highsmith",
      "country": "USA",
      "totalDisplay": "-17",
      "totalValue": -17.0,
      "rounds": [
        "-4",
        "-5",
        "-4",
        "-4"
      ]
    },
    {
      "position": "T9",
      "name": "Zach Bauchou",
      "country": "USA",
      "totalDisplay": "-16",
      "totalValue": -16.0,
      "rounds": [
        "-1",
        "-5",
        "-4",
        "-6"
      ]
    },
    {
      "position": "T9",
      "name": "Thomas Rosenmueller",
      "country": "Germany",
      "totalDisplay": "-16",
      "totalValue": -16.0,
      "rounds": [
        "-2",
        "-6",
        "-4",
        "-4"
      ]
    },
    {
      "position": "T11",
      "name": "Séamus Power",
      "country": "Ireland",
      "totalDisplay": "-15",
      "totalValue": -15.0,
      "rounds": [
        "-4",
        "E",
        "-5",
        "-6"
      ]
    },
    {
      "position": "T11",
      "name": "Davis Bryant",
      "country": "USA",
      "totalDisplay": "-15",
      "totalValue": -15.0,
      "rounds": [
        "-1",
        "-4",
        "-4",
        "-6"
      ]
    },
    {
      "position": "T11",
      "name": "Blades Brown",
      "country": "USA",
      "totalDisplay": "-15",
      "totalValue": -15.0,
      "rounds": [
        "-5",
        "-3",
        "-5",
        "-2"
      ]
    },
    {
      "position": "T11",
      "name": "Max McGreevy",
      "country": "USA",
      "totalDisplay": "-15",
      "totalValue": -15.0,
      "rounds": [
        "-1",
        "-6",
        "-7",
        "-1"
      ]
    },
    {
      "position": "T15",
      "name": "Luke List",
      "country": "USA",
      "totalDisplay": "-14",
      "totalValue": -14.0,
      "rounds": [
        "-1",
        "-2",
        "-3",
        "-8"
      ]
    },
    {
      "position": "T15",
      "name": "Kristoffer Ventura",
      "country": "Norway",
      "totalDisplay": "-14",
      "totalValue": -14.0,
      "rounds": [
        "E",
        "-5",
        "-4",
        "-5"
      ]
    },
    {
      "position": "T15",
      "name": "Marcus Helligkilde",
      "country": "Denmark",
      "totalDisplay": "-14",
      "totalValue": -14.0,
      "rounds": [
        "-3",
        "-4",
        "-3",
        "-4"
      ]
    },
    {
      "position": "T15",
      "name": "Filippo Celli",
      "country": "Italy",
      "totalDisplay": "-14",
      "totalValue": -14.0,
      "rounds": [
        "-5",
        "-2",
        "-3",
        "-4"
      ]
    },
    {
      "position": "T15",
      "name": "Aaron Wise",
      "country": "USA",
      "totalDisplay": "-14",
      "totalValue": -14.0,
      "rounds": [
        "-1",
        "-6",
        "-6",
        "-1"
      ]
    },
    {
      "position": "T20",
      "name": "Jorge Campillo",
      "country": "Spain",
      "totalDisplay": "-13",
      "totalValue": -13.0,
      "rounds": [
        "-2",
        "-3",
        "-3",
        "-5"
      ]
    },
    {
      "position": "T20",
      "name": "Mackenzie Hughes",
      "country": "Canada",
      "totalDisplay": "-13",
      "totalValue": -13.0,
      "rounds": [
        "-6",
        "E",
        "-3",
        "-4"
      ]
    },
    {
      "position": "T20",
      "name": "Nick Dunlap",
      "country": "USA",
      "totalDisplay": "-13",
      "totalValue": -13.0,
      "rounds": [
        "-5",
        "E",
        "-5",
        "-3"
      ]
    },
    {
      "position": "T20",
      "name": "A.J. Ewart",
      "country": "Canada",
      "totalDisplay": "-13",
      "totalValue": -13.0,
      "rounds": [
        "-3",
        "-3",
        "-4",
        "-3"
      ]
    },
    {
      "position": "T24",
      "name": "Renato Paratore",
      "country": "Italy",
      "totalDisplay": "-12",
      "totalValue": -12.0,
      "rounds": [
        "-2",
        "-2",
        "-1",
        "-7"
      ]
    },
    {
      "position": "T24",
      "name": "Kevin Yu",
      "country": "Chinese Taipei",
      "totalDisplay": "-12",
      "totalValue": -12.0,
      "rounds": [
        "-4",
        "-1",
        "-4",
        "-3"
      ]
    },
    {
      "position": "T24",
      "name": "Hayden Springer",
      "country": "USA",
      "totalDisplay": "-12",
      "totalValue": -12.0,
      "rounds": [
        "-3",
        "-2",
        "-5",
        "-2"
      ]
    },
    {
      "position": "T24",
      "name": "Paul Peterson",
      "country": "USA",
      "totalDisplay": "-12",
      "totalValue": -12.0,
      "rounds": [
        "-4",
        "-2",
        "-4",
        "-2"
      ]
    },
    {
      "position": "T24",
      "name": "Joel Dahmen",
      "country": "USA",
      "totalDisplay": "-12",
      "totalValue": -12.0,
      "rounds": [
        "-1",
        "-6",
        "-3",
        "-2"
      ]
    },
    {
      "position": "T24",
      "name": "Johannes Veerman",
      "country": "USA",
      "totalDisplay": "-12",
      "totalValue": -12.0,
      "rounds": [
        "-6",
        "-5",
        "+1",
        "-2"
      ]
    },
    {
      "position": "T30",
      "name": "David Skinns",
      "country": "England",
      "totalDisplay": "-11",
      "totalValue": -11.0,
      "rounds": [
        "+1",
        "-6",
        "-4",
        "-2"
      ]
    },
    {
      "position": "T30",
      "name": "Tom Vaillant",
      "country": "France",
      "totalDisplay": "-11",
      "totalValue": -11.0,
      "rounds": [
        "-2",
        "-4",
        "-3",
        "-2"
      ]
    },
    {
      "position": "T30",
      "name": "John VanDerLaan",
      "country": "USA",
      "totalDisplay": "-11",
      "totalValue": -11.0,
      "rounds": [
        "+1",
        "-4",
        "-7",
        "-1"
      ]
    },
    {
      "position": "T30",
      "name": "Jonathan Byrd",
      "country": "USA",
      "totalDisplay": "-11",
      "totalValue": -11.0,
      "rounds": [
        "-6",
        "E",
        "-5",
        "E"
      ]
    },
    {
      "position": "T34",
      "name": "Carson Young",
      "country": "USA",
      "totalDisplay": "-10",
      "totalValue": -10.0,
      "rounds": [
        "-1",
        "-2",
        "E",
        "-7"
      ]
    },
    {
      "position": "T34",
      "name": "Davis Chatfield",
      "country": "USA",
      "totalDisplay": "-10",
      "totalValue": -10.0,
      "rounds": [
        "-3",
        "E",
        "E",
        "-7"
      ]
    },
    {
      "position": "T34",
      "name": "Jens Dantorp",
      "country": "Sweden",
      "totalDisplay": "-10",
      "totalValue": -10.0,
      "rounds": [
        "-3",
        "-1",
        "-2",
        "-4"
      ]
    },
    {
      "position": "T34",
      "name": "Sebastian Söderberg",
      "country": "Sweden",
      "totalDisplay": "-10",
      "totalValue": -10.0,
      "rounds": [
        "-1",
        "-4",
        "-1",
        "-4"
      ]
    },
    {
      "position": "T34",
      "name": "Peter Malnati",
      "country": "USA",
      "totalDisplay": "-10",
      "totalValue": -10.0,
      "rounds": [
        "-3",
        "-2",
        "-2",
        "-3"
      ]
    },
    {
      "position": "T34",
      "name": "Trace Crowe",
      "country": "USA",
      "totalDisplay": "-10",
      "totalValue": -10.0,
      "rounds": [
        "-1",
        "-4",
        "-2",
        "-3"
      ]
    },
    {
      "position": "T34",
      "name": "Freddy Schott",
      "country": "Germany",
      "totalDisplay": "-10",
      "totalValue": -10.0,
      "rounds": [
        "-2",
        "-3",
        "-3",
        "-2"
      ]
    },
    {
      "position": "T34",
      "name": "Nicolai von Dellingshausen",
      "country": "Germany",
      "totalDisplay": "-10",
      "totalValue": -10.0,
      "rounds": [
        "-1",
        "-2",
        "-6",
        "-1"
      ]
    },
    {
      "position": "T42",
      "name": "Davis Riley",
      "country": "USA",
      "totalDisplay": "-9",
      "totalValue": -9.0,
      "rounds": [
        "E",
        "-3",
        "E",
        "-6"
      ]
    },
    {
      "position": "T42",
      "name": "Keenan Huskey",
      "country": "USA",
      "totalDisplay": "-9",
      "totalValue": -9.0,
      "rounds": [
        "+1",
        "-5",
        "-1",
        "-4"
      ]
    },
    {
      "position": "T42",
      "name": "Justin Lower",
      "country": "USA",
      "totalDisplay": "-9",
      "totalValue": -9.0,
      "rounds": [
        "-3",
        "E",
        "-3",
        "-3"
      ]
    },
    {
      "position": "T42",
      "name": "Beau Hossler",
      "country": "USA",
      "totalDisplay": "-9",
      "totalValue": -9.0,
      "rounds": [
        "-4",
        "-2",
        "E",
        "-3"
      ]
    },
    {
      "position": "T42",
      "name": "Patrick Fishburn",
      "country": "USA",
      "totalDisplay": "-9",
      "totalValue": -9.0,
      "rounds": [
        "-5",
        "-2",
        "E",
        "-2"
      ]
    },
    {
      "position": "T42",
      "name": "Fabián Gómez",
      "country": "Argentina",
      "totalDisplay": "-9",
      "totalValue": -9.0,
      "rounds": [
        "-1",
        "-3",
        "-4",
        "-1"
      ]
    },
    {
      "position": "T48",
      "name": "S.Y. Noh",
      "country": "South Korea",
      "totalDisplay": "-8",
      "totalValue": -8.0,
      "rounds": [
        "-4",
        "+1",
        "+2",
        "-7"
      ]
    },
    {
      "position": "T48",
      "name": "Bill Haas",
      "country": "USA",
      "totalDisplay": "-8",
      "totalValue": -8.0,
      "rounds": [
        "-3",
        "-1",
        "-2",
        "-2"
      ]
    },
    {
      "position": "T48",
      "name": "Garrick Higgo",
      "country": "South Africa",
      "totalDisplay": "-8",
      "totalValue": -8.0,
      "rounds": [
        "E",
        "-4",
        "-2",
        "-2"
      ]
    },
    {
      "position": "T48",
      "name": "Jeffrey Kang",
      "country": "USA",
      "totalDisplay": "-8",
      "totalValue": -8.0,
      "rounds": [
        "-2",
        "-3",
        "-1",
        "-2"
      ]
    },
    {
      "position": "T48",
      "name": "Kiradech Aphibarnrat",
      "country": "Thailand",
      "totalDisplay": "-8",
      "totalValue": -8.0,
      "rounds": [
        "+1",
        "-4",
        "-4",
        "-1"
      ]
    },
    {
      "position": "T48",
      "name": "Camilo Villegas",
      "country": "Colombia",
      "totalDisplay": "-8",
      "totalValue": -8.0,
      "rounds": [
        "-2",
        "-2",
        "-3",
        "-1"
      ]
    },
    {
      "position": "T48",
      "name": "Austin Cook",
      "country": "USA",
      "totalDisplay": "-8",
      "totalValue": -8.0,
      "rounds": [
        "-5",
        "+1",
        "-3",
        "-1"
      ]
    },
    {
      "position": "T48",
      "name": "Brandon Robinson Thompson",
      "country": "England",
      "totalDisplay": "-8",
      "totalValue": -8.0,
      "rounds": [
        "-2",
        "-2",
        "-3",
        "-1"
      ]
    },
    {
      "position": "T48",
      "name": "Romain Langasque",
      "country": "France",
      "totalDisplay": "-8",
      "totalValue": -8.0,
      "rounds": [
        "-4",
        "-2",
        "-1",
        "-1"
      ]
    },
    {
      "position": "T48",
      "name": "Ivan Cantero",
      "country": "Spain",
      "totalDisplay": "-8",
      "totalValue": -8.0,
      "rounds": [
        "-7",
        "-1",
        "+1",
        "-1"
      ]
    },
    {
      "position": "T48",
      "name": "Nick Hardy",
      "country": "USA",
      "totalDisplay": "-8",
      "totalValue": -8.0,
      "rounds": [
        "-1",
        "-5",
        "-2",
        "E"
      ]
    },
    {
      "position": "T48",
      "name": "Brandt Snedeker",
      "country": "USA",
      "totalDisplay": "-8",
      "totalValue": -8.0,
      "rounds": [
        "-2",
        "-4",
        "-2",
        "E"
      ]
    },
    {
      "position": "T48",
      "name": "Chez Reavie",
      "country": "USA",
      "totalDisplay": "-8",
      "totalValue": -8.0,
      "rounds": [
        "-1",
        "-3",
        "-6",
        "+2"
      ]
    },
    {
      "position": "T48",
      "name": "Alejandro Del Rey",
      "country": "Spain",
      "totalDisplay": "-8",
      "totalValue": -8.0,
      "rounds": [
        "-6",
        "-4",
        "-1",
        "+3"
      ]
    },
    {
      "position": "T62",
      "name": "Harry Higgs",
      "country": "USA",
      "totalDisplay": "-7",
      "totalValue": -7.0,
      "rounds": [
        "E",
        "-4",
        "E",
        "-3"
      ]
    },
    {
      "position": "T62",
      "name": "Kevin Roy",
      "country": "USA",
      "totalDisplay": "-7",
      "totalValue": -7.0,
      "rounds": [
        "-2",
        "-1",
        "-2",
        "-2"
      ]
    },
    {
      "position": "T62",
      "name": "Chad Ramey",
      "country": "USA",
      "totalDisplay": "-7",
      "totalValue": -7.0,
      "rounds": [
        "-2",
        "-1",
        "-3",
        "-1"
      ]
    },
    {
      "position": "T62",
      "name": "Chan Kim",
      "country": "USA",
      "totalDisplay": "-7",
      "totalValue": -7.0,
      "rounds": [
        "-5",
        "+1",
        "-2",
        "-1"
      ]
    },
    {
      "position": "T62",
      "name": "Jeong weon Ko",
      "country": "France",
      "totalDisplay": "-7",
      "totalValue": -7.0,
      "rounds": [
        "-2",
        "-2",
        "-4",
        "+1"
      ]
    },
    {
      "position": "T67",
      "name": "Rico Hoey",
      "country": "Philippines",
      "totalDisplay": "-6",
      "totalValue": -6.0,
      "rounds": [
        "-2",
        "-1",
        "E",
        "-3"
      ]
    },
    {
      "position": "T67",
      "name": "Cameron Champ",
      "country": "USA",
      "totalDisplay": "-6",
      "totalValue": -6.0,
      "rounds": [
        "-3",
        "-1",
        "-3",
        "+1"
      ]
    },
    {
      "position": "T69",
      "name": "Hank Lebioda",
      "country": "USA",
      "totalDisplay": "-5",
      "totalValue": -5.0,
      "rounds": [
        "+1",
        "-4",
        "-1",
        "-1"
      ]
    },
    {
      "position": "T69",
      "name": "Alejandro Tosti",
      "country": "Argentina",
      "totalDisplay": "-5",
      "totalValue": -5.0,
      "rounds": [
        "-1",
        "-2",
        "-2",
        "E"
      ]
    },
    {
      "position": "T69",
      "name": "Ben Martin",
      "country": "USA",
      "totalDisplay": "-5",
      "totalValue": -5.0,
      "rounds": [
        "-1",
        "-3",
        "-1",
        "E"
      ]
    },
    {
      "position": "T69",
      "name": "Niklas Nørgaard",
      "country": "Denmark",
      "totalDisplay": "-5",
      "totalValue": -5.0,
      "rounds": [
        "-3",
        "-1",
        "-1",
        "E"
      ]
    },
    {
      "position": "T69",
      "name": "Pontus Nyholm",
      "country": "Sweden",
      "totalDisplay": "-5",
      "totalValue": -5.0,
      "rounds": [
        "-2",
        "-1",
        "-3",
        "+1"
      ]
    },
    {
      "position": "T69",
      "name": "Sebastian Garcia",
      "country": "Spain",
      "totalDisplay": "-5",
      "totalValue": -5.0,
      "rounds": [
        "-4",
        "-2",
        "E",
        "+1"
      ]
    },
    {
      "position": "T69",
      "name": "Christiaan Bezuidenhout",
      "country": "South Africa",
      "totalDisplay": "-5",
      "totalValue": -5.0,
      "rounds": [
        "-3",
        "-3",
        "-2",
        "+3"
      ]
    },
    {
      "position": "T69",
      "name": "Dylan Frittelli",
      "country": "South Africa",
      "totalDisplay": "-5",
      "totalValue": -5.0,
      "rounds": [
        "E",
        "-6",
        "-6",
        "+7"
      ]
    },
    {
      "position": "T77",
      "name": "Rafa Cabrera Bello",
      "country": "Spain",
      "totalDisplay": "-4",
      "totalValue": -4.0,
      "rounds": [
        "-3",
        "-2",
        "E",
        "+1"
      ]
    },
    {
      "position": "T77",
      "name": "Joel Girrbach",
      "country": "Switzerland",
      "totalDisplay": "-4",
      "totalValue": -4.0,
      "rounds": [
        "-3",
        "-1",
        "-2",
        "+2"
      ]
    },
    {
      "position": "T79",
      "name": "Manuel Elvira",
      "country": "Spain",
      "totalDisplay": "-2",
      "totalValue": -2.0,
      "rounds": [
        "+4",
        "-6"
      ]
    },
    {
      "position": "T79",
      "name": "Adam Hadwin",
      "country": "Canada",
      "totalDisplay": "-2",
      "totalValue": -2.0,
      "rounds": [
        "+1",
        "-3"
      ]
    }
  ]
}